{
	"name": "Desktop",
	"layers": [
		{
			"name": "Layer 0",
			"overriden": 0,
			"subLayers": [],
			"instances": [
				{
					"type": "taskbar",
					"properties": {
						"initially-visible": true,
						"initial-animation": "Default",
						"initial-frame": 0,
						"enable-collisions": true,
						"live-preview": false
					},
					"uid": 8,
					"sid": 515816181310533,
					"tags": "",
					"instanceVariables": {},
					"behaviors": {},
					"instanceFolderItem": {
						"sid": 515816181310533,
						"expanded": true
					},
					"showing": true,
					"locked": false,
					"world": {
						"x": 62,
						"y": 952,
						"width": 110,
						"height": 39,
						"originX": 0.5,
						"originY": 0.5,
						"color": [
							1,
							1,
							1,
							1
						],
						"angle": 0,
						"zElevation": 0
					}
				}
			],
			"sid": 173865563891595,
			"effectTypes": [],
			"isInitiallyVisible": true,
			"isInitiallyInteractive": true,
			"isHTMLElementsLayer": false,
			"color": [
				1,
				1,
				1,
				1
			],
			"backgroundColor": [
				1,
				1,
				1,
				1
			],
			"isTransparent": false,
			"parallaxX": 1,
			"parallaxY": 1,
			"scaleRate": 1,
			"forceOwnTexture": false,
			"renderingMode": "3d",
			"drawOrder": "z-order",
			"useRenderCells": false,
			"blendMode": "normal",
			"zElevation": 0,
			"global": false
		},
		{
			"name": "Background",
			"overriden": 0,
			"subLayers": [],
			"instances": [
				{
					"type": "BGGrid",
					"properties": {
						"svg-file": 407922823107874,
						"initially-visible": true,
						"origin": "top-left"
					},
					"uid": 66,
					"sid": 278623165090405,
					"tags": "",
					"instanceVariables": {},
					"behaviors": {},
					"instanceFolderItem": {
						"sid": 278623165090405,
						"expanded": true
					},
					"showing": true,
					"locked": false,
					"world": {
						"x": 0,
						"y": 0,
						"width": 1920,
						"height": 1080,
						"originX": 0,
						"originY": 0,
						"color": [
							1,
							1,
							1,
							1
						],
						"angle": 0,
						"zElevation": 0
					}
				},
				{
					"type": "Taskbar3",
					"properties": {
						"svg-file": 496153029075983,
						"initially-visible": true,
						"origin": "top-left"
					},
					"uid": 7,
					"sid": 629999832178318,
					"tags": "",
					"instanceVariables": {},
					"behaviors": {},
					"instanceFolderItem": {
						"sid": 629999832178318,
						"expanded": true
					},
					"showing": true,
					"locked": false,
					"world": {
						"x": 0,
						"y": 1027,
						"width": 1922,
						"height": 52.54166666666667,
						"originX": 0,
						"originY": 0,
						"color": [
							1,
							1,
							1,
							1
						],
						"angle": 0,
						"zElevation": 0
					}
				}
			],
			"sid": 160399866193774,
			"effectTypes": [],
			"isInitiallyVisible": true,
			"isInitiallyInteractive": true,
			"isHTMLElementsLayer": false,
			"color": [
				1,
				1,
				1,
				1
			],
			"backgroundColor": [
				1,
				1,
				1,
				1
			],
			"isTransparent": true,
			"parallaxX": 1,
			"parallaxY": 1,
			"scaleRate": 1,
			"forceOwnTexture": false,
			"renderingMode": "3d",
			"drawOrder": "z-order",
			"useRenderCells": false,
			"blendMode": "normal",
			"zElevation": 0,
			"global": false
		},
		{
			"name": "EmailLayer",
			"overriden": 0,
			"subLayers": [],
			"instances": [
				{
					"type": "EmailWindow",
					"properties": {
						"left-margin": 16,
						"right-margin": 16,
						"top-margin": 16,
						"bottom-margin": 16,
						"edges": "stretch",
						"fill": "stretch",
						"initially-visible": false,
						"origin": "top-left",
						"seams": "overlap"
					},
					"uid": 13,
					"sid": 986464872803689,
					"tags": "",
					"instanceVariables": {},
					"behaviors": {},
					"instanceFolderItem": {
						"sid": 986464872803689,
						"expanded": true
					},
					"showing": true,
					"locked": false,
					"world": {
						"x": 555,
						"y": 135,
						"width": 363,
						"height": 796,
						"originX": 0,
						"originY": 0,
						"color": [
							1,
							1,
							1,
							1
						],
						"angle": 0,
						"zElevation": 0
					}
				},
				{
					"type": "EmailTitle",
					"properties": {
						"text": "OutBubble",
						"enable-bbcode": true,
						"font": "Arial",
						"size": 25,
						"line-height": 0,
						"bold": false,
						"italic": false,
						"color": [
							0,
							0,
							0,
							1
						],
						"horizontal-alignment": "left",
						"vertical-alignment": "top",
						"wrapping": "word",
						"text-direction": "ltr",
						"icon-set": -1,
						"initially-visible": true,
						"origin": "top-left",
						"read-aloud": false
					},
					"uid": 15,
					"sid": 749799139121358,
					"tags": "",
					"instanceVariables": {},
					"behaviors": {},
					"instanceFolderItem": {
						"sid": 749799139121358,
						"expanded": true
					},
					"showing": true,
					"locked": false,
					"world": {
						"x": 604,
						"y": 175,
						"width": 485,
						"height": 75,
						"originX": 0,
						"originY": 0,
						"color": [
							1,
							1,
							1,
							1
						],
						"angle": 0,
						"zElevation": 0
					}
				},
				{
					"type": "EmailBox",
					"properties": {
						"initially-visible": true,
						"initial-animation": "Animation 1",
						"initial-frame": 0,
						"enable-collisions": true,
						"live-preview": false
					},
					"uid": 17,
					"sid": 861996856131825,
					"tags": "",
					"instanceVariables": {},
					"behaviors": {},
					"instanceFolderItem": {
						"sid": 861996856131825,
						"expanded": true
					},
					"showing": true,
					"locked": false,
					"world": {
						"x": 783.5,
						"y": 733,
						"width": 805,
						"height": 249,
						"originX": 0.5,
						"originY": 0.5,
						"color": [
							1,
							1,
							1,
							1
						],
						"angle": 0,
						"zElevation": 0
					}
				},
				{
					"type": "EmailMessage",
					"properties": {
						"text": "Subject: RE: SEND ME THE MANUSCRIPT NOW!!\nFrom: Bubble\nTo: John @ AngryBubble Publishing\n\nHere's my manuscript, right on time!!",
						"enable-bbcode": true,
						"font": "Arial",
						"size": 24,
						"line-height": 0,
						"bold": false,
						"italic": false,
						"color": [
							0,
							0,
							0,
							1
						],
						"horizontal-alignment": "left",
						"vertical-alignment": "top",
						"wrapping": "word",
						"text-direction": "ltr",
						"icon-set": -1,
						"initially-visible": false,
						"origin": "top-left",
						"read-aloud": false
					},
					"uid": 18,
					"sid": 661169690769736,
					"tags": "",
					"instanceVariables": {},
					"behaviors": {},
					"instanceFolderItem": {
						"sid": 661169690769736,
						"expanded": true
					},
					"showing": true,
					"locked": false,
					"world": {
						"x": 683,
						"y": 430,
						"width": 584,
						"height": 339,
						"originX": 0,
						"originY": 0,
						"color": [
							1,
							1,
							1,
							1
						],
						"angle": 0,
						"zElevation": 0
					}
				},
				{
					"type": "WindowEmail",
					"properties": {
						"svg-file": 535859652001661,
						"initially-visible": true,
						"origin": "top-left"
					},
					"uid": 67,
					"sid": 207693634960939,
					"tags": "",
					"instanceVariables": {},
					"behaviors": {},
					"instanceFolderItem": {
						"sid": 207693634960939,
						"expanded": true
					},
					"showing": true,
					"locked": false,
					"world": {
						"x": 361,
						"y": 107,
						"width": 859,
						"height": 843,
						"originX": 0,
						"originY": 0,
						"color": [
							1,
							1,
							1,
							1
						],
						"angle": 0,
						"zElevation": 0
					}
				},
				{
					"type": "WindowHacker",
					"properties": {
						"svg-file": 850243436012895,
						"initially-visible": false,
						"origin": "top-left"
					},
					"uid": 68,
					"sid": 302537221188373,
					"tags": "",
					"instanceVariables": {},
					"behaviors": {},
					"effects": {
						"Glitch": {
							"isEnabled": true,
							"parameters": {
								"glitchStrength": 0.4,
								"random1": 1,
								"random2": 1,
								"random3": 1,
								"random4": 1
							}
						}
					},
					"instanceFolderItem": {
						"sid": 302537221188373,
						"expanded": true
					},
					"showing": true,
					"locked": false,
					"world": {
						"x": 382,
						"y": 159,
						"width": 859,
						"height": 730,
						"originX": 0,
						"originY": 0,
						"color": [
							1,
							1,
							1,
							1
						],
						"angle": 0,
						"zElevation": 0
					}
				},
				{
					"type": "emailsendbutton",
					"properties": {
						"svg-file": 494411035309217,
						"initially-visible": false,
						"origin": "top-left"
					},
					"uid": 53,
					"sid": 957121073151944,
					"tags": "",
					"instanceVariables": {},
					"behaviors": {},
					"instanceFolderItem": {
						"sid": 957121073151944,
						"expanded": true
					},
					"showing": true,
					"locked": false,
					"world": {
						"x": 1020,
						"y": 867,
						"width": 174,
						"height": 57,
						"originX": 0,
						"originY": 0,
						"color": [
							1,
							1,
							1,
							1
						],
						"angle": 0,
						"zElevation": 0
					}
				}
			],
			"sid": 311829313348835,
			"effectTypes": [
				{
					"effectId": "swirl",
					"name": "Swirl",
					"instance": {
						"isEnabled": true,
						"parameters": {
							"radius": 0.1,
							"angle": 1
						}
					}
				}
			],
			"isInitiallyVisible": true,
			"isInitiallyInteractive": true,
			"isHTMLElementsLayer": false,
			"color": [
				1,
				1,
				1,
				1
			],
			"backgroundColor": [
				1,
				1,
				1,
				1
			],
			"isTransparent": true,
			"parallaxX": 1,
			"parallaxY": 1,
			"scaleRate": 1,
			"forceOwnTexture": false,
			"renderingMode": "3d",
			"drawOrder": "z-order",
			"useRenderCells": false,
			"blendMode": "normal",
			"zElevation": 0,
			"global": false
		},
		{
			"name": "IconLayer",
			"overriden": 0,
			"subLayers": [],
			"instances": [
				{
					"type": "IconDocumentDragArea",
					"properties": {
						"initially-visible": true,
						"initial-animation": "Animation 1",
						"initial-frame": 0,
						"enable-collisions": true,
						"live-preview": false
					},
					"uid": 12,
					"sid": 311597657658780,
					"tags": "",
					"instanceVariables": {},
					"behaviors": {
						"DragDrop": {
							"properties": {
								"axes": "both",
								"enabled": true
							}
						}
					},
					"effects": {
						"Pulse": {
							"isEnabled": true,
							"parameters": {
								"intensity": 1,
								"lighting": 0.5,
								"speed": 10,
								"frequency": 30,
								"center-x": 0.5,
								"center-y": 0.5
							}
						},
						"Noise": {
							"isEnabled": true,
							"parameters": {
								"intensity": 0.4,
								"color": 1
							}
						}
					},
					"sceneGraphData": {
						"parent-uid": null,
						"uid": 12,
						"children": [
							{
								"uid": 3,
								"flags": {
									"x": true,
									"y": true,
									"z": true,
									"w": true,
									"h": true,
									"a": true,
									"o": false,
									"v": false,
									"d": true,
									"sm": "normal"
								}
							},
							{
								"uid": 11,
								"flags": {
									"x": true,
									"y": true,
									"z": true,
									"w": true,
									"h": true,
									"a": true,
									"o": false,
									"v": false,
									"d": true,
									"sm": "normal"
								}
							}
						],
						"flags": {
							"x": true,
							"y": true,
							"z": true,
							"w": true,
							"h": true,
							"a": true,
							"o": false,
							"v": false,
							"d": true,
							"sm": "normal"
						},
						"preview": {
							"transformX": 0,
							"transformY": 0,
							"transformZElevation": 0,
							"transformW": 0,
							"transformH": 0,
							"transformA": 0,
							"transformSX": 0,
							"transformSY": 0,
							"transformO": 0,
							"previewSceneGraph": false
						}
					},
					"instanceFolderItem": {
						"sid": 311597657658780,
						"expanded": true
					},
					"showing": true,
					"locked": false,
					"world": {
						"x": 97,
						"y": 280,
						"width": 178,
						"height": 198,
						"originX": 0.5,
						"originY": 0.5,
						"color": [
							1,
							1,
							1,
							1
						],
						"angle": 0,
						"zElevation": 0
					}
				},
				{
					"type": "IconTrashText",
					"properties": {
						"text": "Trash",
						"enable-bbcode": true,
						"font": "UbuntuSansMono-VariableFont_wght",
						"size": 14,
						"line-height": 0,
						"bold": true,
						"italic": false,
						"color": [
							0,
							0,
							0,
							1
						],
						"horizontal-alignment": "center",
						"vertical-alignment": "top",
						"wrapping": "word",
						"text-direction": "ltr",
						"icon-set": -1,
						"initially-visible": true,
						"origin": "top-left",
						"read-aloud": false
					},
					"uid": 6,
					"sid": 682836241448069,
					"tags": "",
					"instanceVariables": {},
					"behaviors": {},
					"sceneGraphData": {
						"parent-uid": null,
						"uid": 6,
						"flags": {
							"x": true,
							"y": true,
							"z": true,
							"w": true,
							"h": true,
							"a": true,
							"o": false,
							"v": false,
							"d": true,
							"sm": "normal"
						},
						"preview": {
							"transformX": 0,
							"transformY": 0,
							"transformZElevation": 0,
							"transformW": 0,
							"transformH": 0,
							"transformA": 0,
							"transformSX": 0,
							"transformSY": 0,
							"transformO": 0,
							"previewSceneGraph": false
						}
					},
					"instanceFolderItem": {
						"sid": 682836241448069,
						"expanded": true
					},
					"showing": true,
					"locked": false,
					"world": {
						"x": 20,
						"y": 133,
						"width": 160,
						"height": 44,
						"originX": 0,
						"originY": 0,
						"color": [
							1,
							1,
							1,
							1
						],
						"angle": 0,
						"zElevation": 0
					}
				},
				{
					"type": "IconTrashImage",
					"properties": {
						"svg-file": 149523436159345,
						"initially-visible": true,
						"origin": "top-left"
					},
					"uid": 4,
					"sid": 646323016019421,
					"tags": "",
					"instanceVariables": {},
					"behaviors": {},
					"sceneGraphData": {
						"parent-uid": null,
						"uid": 4,
						"flags": {
							"x": true,
							"y": true,
							"z": true,
							"w": true,
							"h": true,
							"a": true,
							"o": false,
							"v": false,
							"d": true,
							"sm": "normal"
						},
						"preview": {
							"transformX": 0,
							"transformY": 0,
							"transformZElevation": 0,
							"transformW": 0,
							"transformH": 0,
							"transformA": 0,
							"transformSX": 0,
							"transformSY": 0,
							"transformO": 0,
							"previewSceneGraph": false
						}
					},
					"instanceFolderItem": {
						"sid": 646323016019421,
						"expanded": true
					},
					"showing": true,
					"locked": false,
					"world": {
						"x": 50,
						"y": 17,
						"width": 100,
						"height": 100,
						"originX": 0,
						"originY": 0,
						"color": [
							1,
							1,
							1,
							1
						],
						"angle": 0,
						"zElevation": 0
					}
				},
				{
					"type": "IconDocumentImage",
					"properties": {
						"svg-file": 239657796726496,
						"initially-visible": true,
						"origin": "top-left"
					},
					"uid": 3,
					"sid": 368658814198085,
					"tags": "",
					"instanceVariables": {},
					"behaviors": {
						"DragDrop": {
							"properties": {
								"axes": "both",
								"enabled": false
							}
						},
						"Tween": {
							"properties": {
								"enabled": true
							}
						}
					},
					"effects": {
						"GlowVertical": {
							"isEnabled": false,
							"parameters": {
								"intensity": 1
							}
						}
					},
					"sceneGraphData": {
						"parent-uid": 12,
						"uid": 3,
						"flags": {
							"x": true,
							"y": true,
							"z": true,
							"w": true,
							"h": true,
							"a": true,
							"o": false,
							"v": false,
							"d": true,
							"sm": "normal"
						},
						"preview": {
							"transformX": 0,
							"transformY": 0,
							"transformZElevation": 0,
							"transformW": 0,
							"transformH": 0,
							"transformA": 0,
							"transformSX": 0,
							"transformSY": 0,
							"transformO": 0,
							"previewSceneGraph": false
						}
					},
					"instanceFolderItem": {
						"sid": 368658814198085,
						"expanded": true
					},
					"showing": true,
					"locked": false,
					"world": {
						"x": 50,
						"y": 195,
						"width": 100,
						"height": 100,
						"originX": 0,
						"originY": 0,
						"color": [
							1,
							1,
							1,
							1
						],
						"angle": 0,
						"zElevation": 0
					}
				},
				{
					"type": "IconDocumentText",
					"properties": {
						"text": "Manuscript Final Final v2 Revised REVISED v2 New Final NewFinal v2.doc",
						"enable-bbcode": true,
						"font": "UbuntuSansMono-VariableFont_wght",
						"size": 14,
						"line-height": 0,
						"bold": true,
						"italic": false,
						"color": [
							0,
							0,
							0,
							1
						],
						"horizontal-alignment": "center",
						"vertical-alignment": "top",
						"wrapping": "character",
						"text-direction": "ltr",
						"icon-set": -1,
						"initially-visible": true,
						"origin": "top-left",
						"read-aloud": false
					},
					"uid": 11,
					"sid": 899514310493094,
					"tags": "",
					"instanceVariables": {},
					"behaviors": {},
					"sceneGraphData": {
						"parent-uid": 12,
						"uid": 11,
						"flags": {
							"x": true,
							"y": true,
							"z": true,
							"w": true,
							"h": true,
							"a": true,
							"o": false,
							"v": false,
							"d": true,
							"sm": "normal"
						},
						"preview": {
							"transformX": 0,
							"transformY": 0,
							"transformZElevation": 0,
							"transformW": 0,
							"transformH": 0,
							"transformA": 0,
							"transformSX": 0,
							"transformSY": 0,
							"transformO": 0,
							"previewSceneGraph": false
						}
					},
					"instanceFolderItem": {
						"sid": 899514310493094,
						"expanded": true
					},
					"showing": true,
					"locked": false,
					"world": {
						"x": 20,
						"y": 314,
						"width": 160,
						"height": 122,
						"originX": 0,
						"originY": 0,
						"color": [
							1,
							1,
							1,
							1
						],
						"angle": 0,
						"zElevation": 0
					}
				},
				{
					"type": "IconBubbleBurst",
					"properties": {
						"initially-visible": true,
						"initial-animation": "Animation 1",
						"initial-frame": 0,
						"enable-collisions": true,
						"live-preview": false
					},
					"uid": 78,
					"sid": 315994905359183,
					"tags": "",
					"instanceVariables": {},
					"behaviors": {},
					"instanceFolderItem": {
						"sid": 315994905359183,
						"expanded": true
					},
					"showing": true,
					"locked": false,
					"world": {
						"x": -183,
						"y": 512,
						"width": 330,
						"height": 330,
						"originX": 0.5,
						"originY": 0.5,
						"color": [
							1,
							1,
							1,
							1
						],
						"angle": 0,
						"zElevation": 0
					}
				}
			],
			"sid": 459963011268446,
			"effectTypes": [],
			"isInitiallyVisible": true,
			"isInitiallyInteractive": true,
			"isHTMLElementsLayer": false,
			"color": [
				1,
				1,
				1,
				1
			],
			"backgroundColor": [
				1,
				1,
				1,
				1
			],
			"isTransparent": true,
			"parallaxX": 1,
			"parallaxY": 1,
			"scaleRate": 1,
			"forceOwnTexture": false,
			"renderingMode": "3d",
			"drawOrder": "z-order",
			"useRenderCells": false,
			"blendMode": "normal",
			"zElevation": 0,
			"global": false
		},
		{
			"name": "PackingBubblesLayer",
			"overriden": 0,
			"subLayers": [],
			"instances": [
				{
					"type": "packingwindow",
					"properties": {
						"svg-file": 229745041746170,
						"initially-visible": true,
						"origin": "top-left"
					},
					"uid": 22,
					"sid": 705610037030840,
					"tags": "",
					"instanceVariables": {},
					"behaviors": {},
					"instanceFolderItem": {
						"sid": 705610037030840,
						"expanded": true
					},
					"showing": true,
					"locked": false,
					"world": {
						"x": 283,
						"y": 85,
						"width": 1285,
						"height": 842,
						"originX": 0,
						"originY": 0,
						"color": [
							1,
							1,
							1,
							1
						],
						"angle": 0,
						"zElevation": 0
					}
				},
				{
					"type": "PackingScoreText",
					"properties": {
						"text": "Text",
						"enable-bbcode": true,
						"font": "Arial",
						"size": 24,
						"line-height": 0,
						"bold": false,
						"italic": false,
						"color": [
							0,
							0,
							0,
							1
						],
						"horizontal-alignment": "left",
						"vertical-alignment": "top",
						"wrapping": "word",
						"text-direction": "ltr",
						"icon-set": -1,
						"initially-visible": false,
						"origin": "top-left",
						"read-aloud": false
					},
					"uid": 61,
					"sid": 346363193517649,
					"tags": "",
					"instanceVariables": {},
					"behaviors": {},
					"instanceFolderItem": {
						"sid": 346363193517649,
						"expanded": true
					},
					"showing": true,
					"locked": false,
					"world": {
						"x": 699,
						"y": 184,
						"width": 589,
						"height": 45,
						"originX": 0,
						"originY": 0,
						"color": [
							1,
							1,
							1,
							1
						],
						"angle": 0,
						"zElevation": 0
					}
				},
				{
					"type": "WrapPopSheet",
					"properties": {
						"svg-file": 683887132913991,
						"initially-visible": true,
						"origin": "top-left"
					},
					"uid": 69,
					"sid": 931926200633726,
					"tags": "",
					"instanceVariables": {},
					"behaviors": {},
					"instanceFolderItem": {
						"sid": 931926200633726,
						"expanded": true
					},
					"showing": true,
					"locked": false,
					"world": {
						"x": 474,
						"y": 236,
						"width": 1083,
						"height": 590,
						"originX": 0,
						"originY": 0,
						"color": [
							1,
							1,
							1,
							1
						],
						"angle": 0,
						"zElevation": 0
					}
				},
				{
					"type": "WrapPopBar",
					"properties": {
						"svg-file": 908679379340249,
						"initially-visible": true,
						"origin": "top-left"
					},
					"uid": 75,
					"sid": 378371233805410,
					"tags": "",
					"instanceVariables": {},
					"behaviors": {},
					"instanceFolderItem": {
						"sid": 378371233805410,
						"expanded": true
					},
					"showing": true,
					"locked": false,
					"world": {
						"x": 492,
						"y": 168,
						"width": 867,
						"height": 35,
						"originX": 0,
						"originY": 0,
						"color": [
							1,
							1,
							1,
							1
						],
						"angle": 0,
						"zElevation": 0
					}
				}
			],
			"sid": 439457540224719,
			"effectTypes": [],
			"isInitiallyVisible": false,
			"isInitiallyInteractive": false,
			"isHTMLElementsLayer": false,
			"color": [
				1,
				1,
				1,
				1
			],
			"backgroundColor": [
				1,
				1,
				1,
				1
			],
			"isTransparent": true,
			"parallaxX": 1,
			"parallaxY": 1,
			"scaleRate": 1,
			"forceOwnTexture": false,
			"renderingMode": "3d",
			"drawOrder": "z-order",
			"useRenderCells": false,
			"blendMode": "normal",
			"zElevation": 0,
			"global": false
		},
		{
			"name": "PackingInnerLayer",
			"overriden": 0,
			"subLayers": [],
			"instances": [
				{
					"type": "packingbubbleunpopped",
					"properties": {
						"svg-file": 566041577405103,
						"initially-visible": true,
						"origin": "top-left"
					},
					"uid": 29,
					"sid": 914881312306152,
					"tags": "",
					"instanceVariables": {
						"hasSpawned": false,
						"originalX": 0,
						"hasPopped": false
					},
					"behaviors": {
						"Tween": {
							"properties": {
								"enabled": true
							}
						}
					},
					"instanceFolderItem": {
						"sid": 914881312306152,
						"expanded": true
					},
					"showing": true,
					"locked": false,
					"world": {
						"x": 336,
						"y": 851,
						"width": 84,
						"height": 84,
						"originX": 0,
						"originY": 0,
						"color": [
							1,
							1,
							1,
							1
						],
						"angle": 0,
						"zElevation": 0
					}
				},
				{
					"type": "PackingPortview",
					"properties": {
						"initially-visible": true,
						"initial-animation": "Animation 1",
						"initial-frame": 0,
						"enable-collisions": true,
						"live-preview": false
					},
					"uid": 57,
					"sid": 697700295300401,
					"tags": "",
					"instanceVariables": {},
					"behaviors": {},
					"instanceFolderItem": {
						"sid": 697700295300401,
						"expanded": true
					},
					"showing": true,
					"locked": false,
					"world": {
						"x": 1793.5,
						"y": 477,
						"width": 473,
						"height": 871,
						"originX": 0.5,
						"originY": 0.5,
						"color": [
							1,
							1,
							1,
							1
						],
						"angle": 0,
						"zElevation": 0,
						"blendMode": "source-out"
					}
				},
				{
					"type": "PackingPortview",
					"properties": {
						"initially-visible": true,
						"initial-animation": "Animation 1",
						"initial-frame": 0,
						"enable-collisions": true,
						"live-preview": false
					},
					"uid": 60,
					"sid": 294857237094009,
					"tags": "",
					"instanceVariables": {},
					"behaviors": {},
					"instanceFolderItem": {
						"sid": 294857237094009,
						"expanded": true
					},
					"showing": true,
					"locked": false,
					"world": {
						"x": 1243,
						"y": -308,
						"width": 1236,
						"height": 367,
						"originX": 0.5,
						"originY": 0.5,
						"color": [
							1,
							1,
							1,
							1
						],
						"angle": 0,
						"zElevation": 0,
						"blendMode": "source-out"
					}
				},
				{
					"type": "WrapPopRoll",
					"properties": {
						"svg-file": 794965248193596,
						"initially-visible": true,
						"origin": "top-left"
					},
					"uid": 70,
					"sid": 884415587513726,
					"tags": "",
					"instanceVariables": {},
					"behaviors": {},
					"instanceFolderItem": {
						"sid": 884415587513726,
						"expanded": true
					},
					"showing": true,
					"locked": false,
					"world": {
						"x": 309,
						"y": 231,
						"width": 297.39102564102564,
						"height": 595,
						"originX": 0,
						"originY": 0,
						"color": [
							1,
							1,
							1,
							1
						],
						"angle": 0,
						"zElevation": 0
					}
				},
				{
					"type": "WrapPopBarFill",
					"properties": {
						"svg-file": 392535753028146,
						"initially-visible": true,
						"origin": "top-left"
					},
					"uid": 76,
					"sid": 203977574497095,
					"tags": "",
					"instanceVariables": {},
					"behaviors": {},
					"instanceFolderItem": {
						"sid": 203977574497095,
						"expanded": true
					},
					"showing": true,
					"locked": false,
					"world": {
						"x": 491,
						"y": 169,
						"width": 867,
						"height": 35,
						"originX": 0,
						"originY": 0,
						"color": [
							1,
							1,
							1,
							1
						],
						"angle": 0,
						"zElevation": 0
					}
				},
				{
					"type": "PackingMaskBar",
					"properties": {
						"initially-visible": true,
						"initial-animation": "Animation 1",
						"initial-frame": 0,
						"enable-collisions": true,
						"live-preview": false
					},
					"uid": 77,
					"sid": 212230158137646,
					"tags": "",
					"instanceVariables": {},
					"behaviors": {},
					"instanceFolderItem": {
						"sid": 212230158137646,
						"expanded": true
					},
					"showing": true,
					"locked": false,
					"world": {
						"x": 1364,
						"y": 189,
						"width": 867,
						"height": 43,
						"originX": 1.012,
						"originY": 0.488,
						"color": [
							1,
							1,
							1,
							1
						],
						"angle": 0,
						"zElevation": 0,
						"blendMode": "source-in"
					}
				}
			],
			"sid": 796429531467666,
			"effectTypes": [],
			"isInitiallyVisible": false,
			"isInitiallyInteractive": false,
			"isHTMLElementsLayer": false,
			"color": [
				1,
				1,
				1,
				1
			],
			"backgroundColor": [
				1,
				1,
				1,
				1
			],
			"isTransparent": true,
			"parallaxX": 1,
			"parallaxY": 1,
			"scaleRate": 1,
			"forceOwnTexture": true,
			"renderingMode": "3d",
			"drawOrder": "z-order",
			"useRenderCells": false,
			"blendMode": "normal",
			"zElevation": 0,
			"global": false
		},
		{
			"name": "Popups",
			"overriden": 0,
			"subLayers": [],
			"instances": [
				{
					"type": "Popup1",
					"properties": {
						"svg-file": 562531298078152,
						"initially-visible": true,
						"origin": "top-left"
					},
					"uid": 19,
					"sid": 958499680313472,
					"tags": "",
					"instanceVariables": {},
					"behaviors": {},
					"sceneGraphData": {
						"parent-uid": null,
						"uid": 19,
						"children": [
							{
								"uid": 20,
								"flags": {
									"x": true,
									"y": true,
									"z": true,
									"w": true,
									"h": true,
									"a": true,
									"o": false,
									"v": false,
									"d": true,
									"sm": "normal"
								}
							}
						],
						"flags": {
							"x": true,
							"y": true,
							"z": true,
							"w": true,
							"h": true,
							"a": true,
							"o": false,
							"v": false,
							"d": true,
							"sm": "normal"
						},
						"preview": {
							"transformX": 0,
							"transformY": 0,
							"transformZElevation": 0,
							"transformW": 0,
							"transformH": 0,
							"transformA": 0,
							"transformSX": 0,
							"transformSY": 0,
							"transformO": 0,
							"previewSceneGraph": false
						}
					},
					"instanceFolderItem": {
						"sid": 958499680313472,
						"expanded": true
					},
					"showing": true,
					"locked": false,
					"world": {
						"x": 609,
						"y": 338,
						"width": 703,
						"height": 239,
						"originX": 0,
						"originY": 0,
						"color": [
							1,
							1,
							1,
							1
						],
						"angle": 0,
						"zElevation": 0
					}
				},
				{
					"type": "closeButton",
					"properties": {
						"svg-file": 572746425494573,
						"initially-visible": true,
						"origin": "top-left"
					},
					"uid": 20,
					"sid": 858298817578391,
					"tags": "",
					"instanceVariables": {},
					"behaviors": {},
					"sceneGraphData": {
						"parent-uid": 19,
						"uid": 20,
						"flags": {
							"x": true,
							"y": true,
							"z": true,
							"w": true,
							"h": true,
							"a": true,
							"o": false,
							"v": false,
							"d": true,
							"sm": "normal"
						},
						"preview": {
							"transformX": 0,
							"transformY": 0,
							"transformZElevation": 0,
							"transformW": 0,
							"transformH": 0,
							"transformA": 0,
							"transformSX": 0,
							"transformSY": 0,
							"transformO": 0,
							"previewSceneGraph": false
						}
					},
					"instanceFolderItem": {
						"sid": 858298817578391,
						"expanded": true
					},
					"showing": true,
					"locked": false,
					"world": {
						"x": 1205,
						"y": 310,
						"width": 88,
						"height": 88,
						"originX": 0,
						"originY": 0,
						"color": [
							1,
							1,
							1,
							1
						],
						"angle": 0,
						"zElevation": 0
					}
				}
			],
			"sid": 589855587378255,
			"effectTypes": [],
			"isInitiallyVisible": false,
			"isInitiallyInteractive": false,
			"isHTMLElementsLayer": false,
			"color": [
				1,
				1,
				1,
				1
			],
			"backgroundColor": [
				1,
				1,
				1,
				1
			],
			"isTransparent": true,
			"parallaxX": 1,
			"parallaxY": 1,
			"scaleRate": 1,
			"forceOwnTexture": false,
			"renderingMode": "3d",
			"drawOrder": "z-order",
			"useRenderCells": false,
			"blendMode": "normal",
			"zElevation": 0,
			"global": false
		},
		{
			"name": "BubbleGuyLayer",
			"overriden": 0,
			"subLayers": [],
			"instances": [
				{
					"type": "bubbleGuyWindow",
					"properties": {
						"svg-file": 126350709594234,
						"initially-visible": true,
						"origin": "top-left"
					},
					"uid": 35,
					"sid": 819474848746584,
					"tags": "",
					"instanceVariables": {},
					"behaviors": {},
					"instanceFolderItem": {
						"sid": 819474848746584,
						"expanded": true
					},
					"showing": true,
					"locked": false,
					"world": {
						"x": 285,
						"y": 94,
						"width": 1277,
						"height": 834,
						"originX": 0,
						"originY": 0,
						"color": [
							1,
							1,
							1,
							1
						],
						"angle": 0,
						"zElevation": 0
					}
				}
			],
			"sid": 886605401946286,
			"effectTypes": [],
			"isInitiallyVisible": false,
			"isInitiallyInteractive": false,
			"isHTMLElementsLayer": false,
			"color": [
				1,
				1,
				1,
				1
			],
			"backgroundColor": [
				1,
				1,
				1,
				1
			],
			"isTransparent": true,
			"parallaxX": 1,
			"parallaxY": 1,
			"scaleRate": 1,
			"forceOwnTexture": true,
			"renderingMode": "3d",
			"drawOrder": "z-order",
			"useRenderCells": false,
			"blendMode": "normal",
			"zElevation": 0,
			"global": false
		},
		{
			"name": "BubbleGuyInnerLayer",
			"overriden": 0,
			"subLayers": [],
			"instances": [
				{
					"type": "bubbleguybody",
					"properties": {
						"svg-file": 898312691504848,
						"initially-visible": true,
						"origin": "top-left"
					},
					"uid": 37,
					"sid": 404456869671166,
					"tags": "",
					"instanceVariables": {},
					"behaviors": {
						"8Direction": {
							"properties": {
								"max-speed": 200,
								"acceleration": 200,
								"deceleration": 200,
								"directions": "dir-8",
								"set-angle": "no",
								"allow-sliding": false,
								"default-controls": true,
								"enabled": true
							}
						},
						"Rotate": {
							"properties": {
								"speed": 20,
								"acceleration": 0,
								"enabled": true,
								"live-preview": false
							}
						}
					},
					"sceneGraphData": {
						"parent-uid": null,
						"uid": 37,
						"children": [
							{
								"uid": 40,
								"flags": {
									"x": true,
									"y": true,
									"z": true,
									"w": true,
									"h": true,
									"a": true,
									"o": false,
									"v": false,
									"d": true,
									"sm": "normal"
								}
							},
							{
								"uid": 44,
								"flags": {
									"x": true,
									"y": true,
									"z": true,
									"w": true,
									"h": true,
									"a": true,
									"o": false,
									"v": false,
									"d": true,
									"sm": "normal"
								}
							},
							{
								"uid": 36,
								"flags": {
									"x": true,
									"y": true,
									"z": true,
									"w": true,
									"h": true,
									"a": true,
									"o": false,
									"v": false,
									"d": true,
									"sm": "normal"
								}
							},
							{
								"uid": 38,
								"flags": {
									"x": true,
									"y": true,
									"z": true,
									"w": true,
									"h": true,
									"a": true,
									"o": false,
									"v": false,
									"d": true,
									"sm": "normal"
								}
							}
						],
						"flags": {
							"x": true,
							"y": true,
							"z": true,
							"w": true,
							"h": true,
							"a": true,
							"o": false,
							"v": false,
							"d": true,
							"sm": "normal"
						},
						"preview": {
							"transformX": 0,
							"transformY": 0,
							"transformZElevation": 0,
							"transformW": 0,
							"transformH": 0,
							"transformA": 0,
							"transformSX": 0,
							"transformSY": 0,
							"transformO": 0,
							"previewSceneGraph": false
						}
					},
					"instanceFolderItem": {
						"sid": 404456869671166,
						"expanded": true
					},
					"showing": true,
					"locked": false,
					"world": {
						"x": 632,
						"y": 672,
						"width": 89,
						"height": 192,
						"originX": 0,
						"originY": 0,
						"color": [
							1,
							1,
							1,
							1
						],
						"angle": 5.9266258352974255,
						"zElevation": 0
					}
				},
				{
					"type": "bubbleguybad",
					"properties": {
						"svg-file": 751257222837638,
						"initially-visible": true,
						"origin": "top-left"
					},
					"uid": 42,
					"sid": 233815620332558,
					"tags": "",
					"instanceVariables": {},
					"behaviors": {
						"MoveTo": {
							"properties": {
								"max-speed": 200,
								"acceleration": 400,
								"deceleration": 400,
								"rotate-speed": 0,
								"set-angle": false,
								"stop-on-solids": false,
								"enabled": true
							}
						}
					},
					"instanceFolderItem": {
						"sid": 233815620332558,
						"expanded": true
					},
					"showing": true,
					"locked": false,
					"world": {
						"x": 918,
						"y": 685,
						"width": 42,
						"height": 40,
						"originX": 0,
						"originY": 0,
						"color": [
							1,
							1,
							1,
							1
						],
						"angle": 0,
						"zElevation": 0
					}
				},
				{
					"type": "bubbleguygood",
					"properties": {
						"svg-file": 633102948183305,
						"initially-visible": true,
						"origin": "top-left"
					},
					"uid": 43,
					"sid": 297689674633698,
					"tags": "",
					"instanceVariables": {},
					"behaviors": {
						"MoveTo": {
							"properties": {
								"max-speed": 170,
								"acceleration": 30,
								"deceleration": 600,
								"rotate-speed": 0,
								"set-angle": false,
								"stop-on-solids": false,
								"enabled": true
							}
						}
					},
					"instanceFolderItem": {
						"sid": 297689674633698,
						"expanded": true
					},
					"showing": true,
					"locked": false,
					"world": {
						"x": 1062,
						"y": 700,
						"width": 45,
						"height": 44,
						"originX": 0,
						"originY": 0,
						"color": [
							1,
							1,
							1,
							1
						],
						"angle": 0,
						"zElevation": 0
					}
				},
				{
					"type": "BubbleGuyLimb",
					"properties": {
						"initially-visible": true,
						"initial-animation": "Animation 1",
						"initial-frame": 0,
						"enable-collisions": true,
						"live-preview": false
					},
					"uid": 44,
					"sid": 868516442394490,
					"tags": "",
					"instanceVariables": {},
					"behaviors": {},
					"sceneGraphData": {
						"parent-uid": 37,
						"uid": 44,
						"flags": {
							"x": true,
							"y": true,
							"z": true,
							"w": true,
							"h": true,
							"a": true,
							"o": false,
							"v": false,
							"d": true,
							"sm": "normal"
						},
						"preview": {
							"transformX": 0,
							"transformY": 0,
							"transformZElevation": 0,
							"transformW": 0,
							"transformH": 0,
							"transformA": 0,
							"transformSX": 0,
							"transformSY": 0,
							"transformO": 0,
							"previewSceneGraph": false
						}
					},
					"instanceFolderItem": {
						"sid": 868516442394490,
						"expanded": true
					},
					"showing": true,
					"locked": false,
					"world": {
						"x": 690.0438607749162,
						"y": 784.9058913730178,
						"width": 16,
						"height": 16,
						"originX": 0.16017316017316016,
						"originY": 0.168141592920354,
						"color": [
							1,
							1,
							1,
							1
						],
						"angle": 1.2463592006357744,
						"zElevation": 0
					}
				},
				{
					"type": "BubbleGuyLimb",
					"properties": {
						"initially-visible": true,
						"initial-animation": "Animation 1",
						"initial-frame": 0,
						"enable-collisions": true,
						"live-preview": false
					},
					"uid": 36,
					"sid": 583994616987868,
					"tags": "",
					"instanceVariables": {},
					"behaviors": {},
					"sceneGraphData": {
						"parent-uid": 37,
						"uid": 36,
						"flags": {
							"x": true,
							"y": true,
							"z": true,
							"w": true,
							"h": true,
							"a": true,
							"o": false,
							"v": false,
							"d": true,
							"sm": "normal"
						},
						"preview": {
							"transformX": 0,
							"transformY": 0,
							"transformZElevation": 0,
							"transformW": 0,
							"transformH": 0,
							"transformA": 0,
							"transformSX": 0,
							"transformSY": 0,
							"transformO": 0,
							"previewSceneGraph": false
						}
					},
					"instanceFolderItem": {
						"sid": 583994616987868,
						"expanded": true
					},
					"showing": true,
					"locked": false,
					"world": {
						"x": 736.8109764633488,
						"y": 762.9108262324702,
						"width": 16,
						"height": 16,
						"originX": 0.16017316017316016,
						"originY": 0.168141592920354,
						"color": [
							1,
							1,
							1,
							1
						],
						"angle": 6.093887385471443,
						"zElevation": 0
					}
				},
				{
					"type": "BubbleGuyLimb",
					"properties": {
						"initially-visible": true,
						"initial-animation": "Animation 1",
						"initial-frame": 0,
						"enable-collisions": true,
						"live-preview": false
					},
					"uid": 38,
					"sid": 243166774526817,
					"tags": "",
					"instanceVariables": {},
					"behaviors": {},
					"sceneGraphData": {
						"parent-uid": 37,
						"uid": 38,
						"flags": {
							"x": true,
							"y": true,
							"z": true,
							"w": true,
							"h": true,
							"a": true,
							"o": false,
							"v": false,
							"d": true,
							"sm": "normal"
						},
						"preview": {
							"transformX": 0,
							"transformY": 0,
							"transformZElevation": 0,
							"transformW": 0,
							"transformH": 0,
							"transformA": 0,
							"transformSX": 0,
							"transformSY": 0,
							"transformO": 0,
							"previewSceneGraph": false
						}
					},
					"instanceFolderItem": {
						"sid": 243166774526817,
						"expanded": true
					},
					"showing": true,
					"locked": false,
					"world": {
						"x": 724.8402516701267,
						"y": 733.809135952062,
						"width": 16,
						"height": 16,
						"originX": 0.16017316017316016,
						"originY": 0.168141592920354,
						"color": [
							1,
							1,
							1,
							1
						],
						"angle": 5.059179380251717,
						"zElevation": 0
					}
				},
				{
					"type": "BubbleGuyLimb",
					"properties": {
						"initially-visible": true,
						"initial-animation": "Animation 1",
						"initial-frame": 0,
						"enable-collisions": true,
						"live-preview": false
					},
					"uid": 40,
					"sid": 400415419199049,
					"tags": "",
					"instanceVariables": {},
					"behaviors": {},
					"sceneGraphData": {
						"parent-uid": 37,
						"uid": 40,
						"flags": {
							"x": true,
							"y": true,
							"z": true,
							"w": true,
							"h": true,
							"a": true,
							"o": false,
							"v": false,
							"d": true,
							"sm": "normal"
						},
						"preview": {
							"transformX": 0,
							"transformY": 0,
							"transformZElevation": 0,
							"transformW": 0,
							"transformH": 0,
							"transformA": 0,
							"transformSX": 0,
							"transformSY": 0,
							"transformO": 0,
							"previewSceneGraph": false
						}
					},
					"instanceFolderItem": {
						"sid": 400415419199049,
						"expanded": true
					},
					"showing": true,
					"locked": false,
					"world": {
						"x": 673.2534611765827,
						"y": 756.7543382791783,
						"width": 16,
						"height": 16,
						"originX": 0.16017316017316016,
						"originY": 0.168141592920354,
						"color": [
							1,
							1,
							1,
							1
						],
						"angle": 2.2503163261841292,
						"zElevation": 0
					}
				},
				{
					"type": "BubbleGuyMask",
					"properties": {
						"initially-visible": true,
						"initial-animation": "Animation 1",
						"initial-frame": 0,
						"enable-collisions": true,
						"live-preview": false
					},
					"uid": 63,
					"sid": 701195044154897,
					"tags": "",
					"instanceVariables": {},
					"behaviors": {},
					"instanceFolderItem": {
						"sid": 701195044154897,
						"expanded": true
					},
					"showing": true,
					"locked": false,
					"world": {
						"x": 928,
						"y": 1125,
						"width": 1342,
						"height": 408,
						"originX": 0.5,
						"originY": 0.5,
						"color": [
							1,
							1,
							1,
							1
						],
						"angle": 0,
						"zElevation": 0,
						"blendMode": "source-in"
					}
				},
				{
					"type": "BubbleGuyMask",
					"properties": {
						"initially-visible": true,
						"initial-animation": "Animation 1",
						"initial-frame": 0,
						"enable-collisions": true,
						"live-preview": false
					},
					"uid": 64,
					"sid": 998519075890846,
					"tags": "",
					"instanceVariables": {},
					"behaviors": {},
					"instanceFolderItem": {
						"sid": 998519075890846,
						"expanded": true
					},
					"showing": true,
					"locked": false,
					"world": {
						"x": 146,
						"y": 540,
						"width": 293,
						"height": 1086,
						"originX": 0.5,
						"originY": 0.5,
						"color": [
							1,
							1,
							1,
							1
						],
						"angle": 0,
						"zElevation": 0,
						"blendMode": "source-in"
					}
				},
				{
					"type": "BubbleGuyMask",
					"properties": {
						"initially-visible": true,
						"initial-animation": "Animation 1",
						"initial-frame": 0,
						"enable-collisions": true,
						"live-preview": false
					},
					"uid": 65,
					"sid": 811577610237043,
					"tags": "",
					"instanceVariables": {},
					"behaviors": {},
					"instanceFolderItem": {
						"sid": 811577610237043,
						"expanded": true
					},
					"showing": true,
					"locked": false,
					"world": {
						"x": 931,
						"y": 25,
						"width": 1313,
						"height": 255,
						"originX": 0.5,
						"originY": 0.5,
						"color": [
							1,
							1,
							1,
							1
						],
						"angle": 0,
						"zElevation": 0,
						"blendMode": "source-in"
					}
				},
				{
					"type": "BubbleGuyMask",
					"properties": {
						"initially-visible": true,
						"initial-animation": "Animation 1",
						"initial-frame": 0,
						"enable-collisions": true,
						"live-preview": false
					},
					"uid": 62,
					"sid": 886148906601396,
					"tags": "",
					"instanceVariables": {},
					"behaviors": {},
					"instanceFolderItem": {
						"sid": 886148906601396,
						"expanded": true
					},
					"showing": true,
					"locked": false,
					"world": {
						"x": 1760,
						"y": 552.5,
						"width": 423,
						"height": 1121,
						"originX": 0.5,
						"originY": 0.5,
						"color": [
							1,
							1,
							1,
							1
						],
						"angle": 0,
						"zElevation": 0,
						"blendMode": "source-in"
					}
				}
			],
			"sid": 981819555887672,
			"effectTypes": [],
			"isInitiallyVisible": false,
			"isInitiallyInteractive": false,
			"isHTMLElementsLayer": false,
			"color": [
				1,
				1,
				1,
				1
			],
			"backgroundColor": [
				1,
				1,
				1,
				1
			],
			"isTransparent": true,
			"parallaxX": 1,
			"parallaxY": 1,
			"scaleRate": 1,
			"forceOwnTexture": true,
			"renderingMode": "3d",
			"drawOrder": "z-order",
			"useRenderCells": false,
			"blendMode": "normal",
			"zElevation": 0,
			"global": false
		},
		{
			"name": "SnakeLayer",
			"overriden": 0,
			"subLayers": [],
			"instances": [
				{
					"type": "SnakeWindowInner",
					"properties": {
						"initially-visible": true,
						"initial-animation": "Animation 1",
						"initial-frame": 0,
						"enable-collisions": true,
						"live-preview": false
					},
					"uid": 51,
					"sid": 529558518241779,
					"tags": "",
					"instanceVariables": {},
					"behaviors": {},
					"instanceFolderItem": {
						"sid": 529558518241779,
						"expanded": true
					},
					"showing": true,
					"locked": false,
					"world": {
						"x": 524,
						"y": 153,
						"width": 776,
						"height": 739,
						"originX": 0,
						"originY": 0,
						"color": [
							1,
							1,
							1,
							1
						],
						"angle": 0,
						"zElevation": 0
					}
				},
				{
					"type": "SnakeWindow",
					"properties": {
						"svg-file": 765853252116692,
						"initially-visible": true,
						"origin": "top-left"
					},
					"uid": 41,
					"sid": 294695512399517,
					"tags": "",
					"instanceVariables": {},
					"behaviors": {},
					"instanceFolderItem": {
						"sid": 294695512399517,
						"expanded": true
					},
					"showing": true,
					"locked": false,
					"world": {
						"x": 324,
						"y": 67,
						"width": 1277,
						"height": 834,
						"originX": 0,
						"originY": 0,
						"color": [
							1,
							1,
							1,
							1
						],
						"angle": 0,
						"zElevation": 0
					}
				},
				{
					"type": "rubberduck",
					"properties": {
						"svg-file": 709440639392148,
						"initially-visible": true,
						"origin": "top-left"
					},
					"uid": 45,
					"sid": 128581443924038,
					"tags": "",
					"instanceVariables": {},
					"behaviors": {},
					"instanceFolderItem": {
						"sid": 128581443924038,
						"expanded": true
					},
					"showing": true,
					"locked": false,
					"world": {
						"x": 333,
						"y": 285,
						"width": 96,
						"height": 96,
						"originX": 0,
						"originY": 0,
						"color": [
							1,
							1,
							1,
							1
						],
						"angle": 0,
						"zElevation": 0
					}
				},
				{
					"type": "SnakeBubbleSprite",
					"properties": {
						"initially-visible": true,
						"initial-animation": "Animation 1",
						"initial-frame": 0,
						"enable-collisions": true,
						"live-preview": false
					},
					"uid": 50,
					"sid": 266851883863828,
					"tags": "",
					"instanceVariables": {
						"Age": 0
					},
					"behaviors": {
						"Solid": {
							"properties": {
								"enabled": true,
								"tags": ""
							}
						}
					},
					"instanceFolderItem": {
						"sid": 266851883863828,
						"expanded": true
					},
					"showing": true,
					"locked": false,
					"world": {
						"x": 1950,
						"y": 388,
						"width": 96,
						"height": 96,
						"originX": 0.00875,
						"originY": 0.00375,
						"color": [
							1,
							1,
							1,
							1
						],
						"angle": 0,
						"zElevation": 0
					}
				},
				{
					"type": "SnakeBottle",
					"properties": {
						"initially-visible": true,
						"initial-animation": "Animation 1",
						"initial-frame": 0,
						"enable-collisions": true,
						"live-preview": false
					},
					"uid": 49,
					"sid": 112867269671461,
					"tags": "",
					"instanceVariables": {},
					"behaviors": {},
					"instanceFolderItem": {
						"sid": 112867269671461,
						"expanded": true
					},
					"showing": true,
					"locked": false,
					"world": {
						"x": 1971,
						"y": 538,
						"width": 96,
						"height": 96,
						"originX": 0,
						"originY": 0,
						"color": [
							1,
							1,
							1,
							1
						],
						"angle": 0,
						"zElevation": 0
					}
				},
				{
					"type": "SnakeBoundary",
					"properties": {
						"initially-visible": true,
						"initial-animation": "Animation 1",
						"initial-frame": 0,
						"enable-collisions": true,
						"live-preview": false
					},
					"uid": 56,
					"sid": 528193043689633,
					"tags": "",
					"instanceVariables": {},
					"behaviors": {},
					"instanceFolderItem": {
						"sid": 528193043689633,
						"expanded": true
					},
					"showing": true,
					"locked": false,
					"world": {
						"x": 326,
						"y": 283,
						"width": 250,
						"height": 250,
						"originX": 0.5,
						"originY": 0.5,
						"color": [
							1,
							1,
							1,
							1
						],
						"angle": 0,
						"zElevation": 0
					}
				}
			],
			"sid": 290574164263735,
			"effectTypes": [],
			"isInitiallyVisible": false,
			"isInitiallyInteractive": false,
			"isHTMLElementsLayer": false,
			"color": [
				1,
				1,
				1,
				1
			],
			"backgroundColor": [
				1,
				1,
				1,
				1
			],
			"isTransparent": true,
			"parallaxX": 1,
			"parallaxY": 1,
			"scaleRate": 1,
			"forceOwnTexture": false,
			"renderingMode": "3d",
			"drawOrder": "z-order",
			"useRenderCells": false,
			"blendMode": "normal",
			"zElevation": 0,
			"global": false
		},
		{
			"name": "SuccessScreen",
			"overriden": 0,
			"subLayers": [],
			"instances": [
				{
					"type": "StandardText",
					"properties": {
						"text": "StandardText",
						"enable-bbcode": true,
						"font": "UbuntuSansMono-VariableFont_wght",
						"size": 24,
						"line-height": 0,
						"bold": false,
						"italic": false,
						"color": [
							0,
							0,
							0,
							1
						],
						"horizontal-alignment": "left",
						"vertical-alignment": "top",
						"wrapping": "word",
						"text-direction": "ltr",
						"icon-set": -1,
						"initially-visible": true,
						"origin": "top-left",
						"read-aloud": false
					},
					"uid": 54,
					"sid": 631701455917377,
					"tags": "",
					"instanceVariables": {},
					"behaviors": {},
					"template": {
						"mode": "template",
						"templateName": "StandardTextTemplte",
						"sourceTemplateName": "",
						"replicaHierarchyInSyncWithTemplate": false,
						"templatePropagateHierarchyChanges": true,
						"replicaIgnoreTemplateHierarchyChanges": false,
						"components": [
							{
								"id": "plugin",
								"component": [
									{
										"key": "plugin",
										"state": [
											[
												"text",
												true
											],
											[
												"enable-bbcode",
												true
											],
											[
												"font",
												true
											],
											[
												"size",
												true
											],
											[
												"line-height",
												true
											],
											[
												"bold",
												true
											],
											[
												"italic",
												true
											],
											[
												"color",
												true
											],
											[
												"horizontal-alignment",
												true
											],
											[
												"vertical-alignment",
												true
											],
											[
												"wrapping",
												true
											],
											[
												"text-direction",
												true
											],
											[
												"icon-set",
												true
											],
											[
												"initially-visible",
												true
											],
											[
												"origin",
												true
											],
											[
												"read-aloud",
												true
											]
										]
									}
								]
							},
							{
								"id": "instance-variable",
								"component": [
									{
										"key": "instance-variable",
										"state": []
									}
								]
							},
							{
								"id": "behavior",
								"component": []
							},
							{
								"id": "effect",
								"component": []
							},
							{
								"id": "world-instance",
								"component": [
									{
										"key": "world-instance",
										"state": [
											[
												"x",
												false
											],
											[
												"y",
												false
											],
											[
												"z",
												true
											],
											[
												"w",
												true
											],
											[
												"h",
												true
											],
											[
												"a",
												true
											],
											[
												"o",
												true
											],
											[
												"c",
												true
											],
											[
												"sx",
												true
											],
											[
												"sy",
												true
											],
											[
												"bm",
												true
											],
											[
												"twpx",
												true
											],
											[
												"twpy",
												true
											],
											[
												"twpz",
												true
											],
											[
												"twpw",
												true
											],
											[
												"twph",
												true
											],
											[
												"twpa",
												true
											],
											[
												"dwp",
												true
											],
											[
												"ssm",
												true
											]
										]
									}
								]
							}
						],
						"replicasUIDs": null
					},
					"instanceFolderItem": {
						"sid": 631701455917377,
						"expanded": true
					},
					"showing": true,
					"locked": false,
					"world": {
						"x": 2060,
						"y": 405,
						"width": 200,
						"height": 64,
						"originX": 0,
						"originY": 0,
						"color": [
							1,
							1,
							1,
							1
						],
						"angle": 0,
						"zElevation": 0
					}
				},
				{
					"type": "WindowAmused",
					"properties": {
						"svg-file": 645051556880997,
						"initially-visible": true,
						"origin": "top-left"
					},
					"uid": 58,
					"sid": 905124757160879,
					"tags": "",
					"instanceVariables": {},
					"behaviors": {},
					"effects": {
						"Glitch": {
							"isEnabled": true,
							"parameters": {
								"glitchStrength": 0.2,
								"random1": 1,
								"random2": 1,
								"random3": 1,
								"random4": 1
							}
						}
					},
					"instanceFolderItem": {
						"sid": 905124757160879,
						"expanded": true
					},
					"showing": true,
					"locked": false,
					"world": {
						"x": 328,
						"y": 91,
						"width": 1277,
						"height": 834,
						"originX": 0,
						"originY": 0,
						"color": [
							1,
							1,
							1,
							1
						],
						"angle": 0,
						"zElevation": 0
					}
				}
			],
			"sid": 341095703762929,
			"effectTypes": [
				{
					"effectId": "Coolok_Glitch",
					"name": "Glitch",
					"instance": {
						"isEnabled": true,
						"parameters": {
							"glitchStrength": 0,
							"random1": 0.5,
							"random2": 1,
							"random3": 1,
							"random4": 1
						}
					}
				},
				{
					"effectId": "warpripple",
					"name": "WarpRipple",
					"instance": {
						"isEnabled": true,
						"parameters": {
							"frequency": 3,
							"amplitude": 0,
							"speed": -2
						}
					}
				}
			],
			"isInitiallyVisible": false,
			"isInitiallyInteractive": false,
			"isHTMLElementsLayer": false,
			"color": [
				1,
				1,
				1,
				1
			],
			"backgroundColor": [
				1,
				1,
				1,
				1
			],
			"isTransparent": true,
			"parallaxX": 1,
			"parallaxY": 1,
			"scaleRate": 1,
			"forceOwnTexture": false,
			"renderingMode": "3d",
			"drawOrder": "z-order",
			"useRenderCells": false,
			"blendMode": "normal",
			"zElevation": 0,
			"global": false
		},
		{
			"name": "GameIconsLayer",
			"overriden": 0,
			"subLayers": [],
			"instances": [
				{
					"type": "SnakeIconClick",
					"properties": {
						"initially-visible": true,
						"initial-animation": "Animation 1",
						"initial-frame": 0,
						"enable-collisions": true,
						"live-preview": false
					},
					"uid": 48,
					"sid": 131362121694831,
					"tags": "",
					"instanceVariables": {},
					"behaviors": {
						"DragDrop": {
							"properties": {
								"axes": "both",
								"enabled": true
							}
						}
					},
					"effects": {
						"Pulse": {
							"isEnabled": true,
							"parameters": {
								"intensity": 1,
								"lighting": 0.5,
								"speed": 10,
								"frequency": 30,
								"center-x": 0.5,
								"center-y": 0.5
							}
						},
						"Noise": {
							"isEnabled": true,
							"parameters": {
								"intensity": 0.4,
								"color": 1
							}
						}
					},
					"sceneGraphData": {
						"parent-uid": null,
						"uid": 48,
						"flags": {
							"x": true,
							"y": true,
							"z": true,
							"w": true,
							"h": true,
							"a": true,
							"o": false,
							"v": false,
							"d": true,
							"sm": "normal"
						},
						"preview": {
							"transformX": 0,
							"transformY": 0,
							"transformZElevation": 0,
							"transformW": 0,
							"transformH": 0,
							"transformA": 0,
							"transformSX": 0,
							"transformSY": 0,
							"transformO": 0,
							"previewSceneGraph": false
						}
					},
					"instanceFolderItem": {
						"sid": 131362121694831,
						"expanded": true
					},
					"showing": true,
					"locked": false,
					"world": {
						"x": 107,
						"y": 839,
						"width": 178,
						"height": 185,
						"originX": 0.5,
						"originY": 0.5,
						"color": [
							1,
							1,
							1,
							1
						],
						"angle": 0,
						"zElevation": 0
					}
				},
				{
					"type": "BubbleGuyIconImage",
					"properties": {
						"initially-visible": true,
						"initial-animation": "Animation 1",
						"initial-frame": 0,
						"enable-collisions": true,
						"live-preview": false
					},
					"uid": 32,
					"sid": 704261742420380,
					"tags": "",
					"instanceVariables": {},
					"behaviors": {
						"DragDrop": {
							"properties": {
								"axes": "both",
								"enabled": true
							}
						}
					},
					"effects": {
						"Pulse": {
							"isEnabled": true,
							"parameters": {
								"intensity": 1,
								"lighting": 0.5,
								"speed": 10,
								"frequency": 30,
								"center-x": 0.5,
								"center-y": 0.5
							}
						},
						"Noise": {
							"isEnabled": true,
							"parameters": {
								"intensity": 0.4,
								"color": 1
							}
						}
					},
					"sceneGraphData": {
						"parent-uid": null,
						"uid": 32,
						"flags": {
							"x": true,
							"y": true,
							"z": true,
							"w": true,
							"h": true,
							"a": true,
							"o": false,
							"v": false,
							"d": true,
							"sm": "normal"
						},
						"preview": {
							"transformX": 0,
							"transformY": 0,
							"transformZElevation": 0,
							"transformW": 0,
							"transformH": 0,
							"transformA": 0,
							"transformSX": 0,
							"transformSY": 0,
							"transformO": 0,
							"previewSceneGraph": false
						}
					},
					"instanceFolderItem": {
						"sid": 704261742420380,
						"expanded": true
					},
					"showing": true,
					"locked": false,
					"world": {
						"x": 99,
						"y": 690,
						"width": 178,
						"height": 185,
						"originX": 0.5,
						"originY": 0.5,
						"color": [
							1,
							1,
							1,
							1
						],
						"angle": 0,
						"zElevation": 0
					}
				},
				{
					"type": "PackingGameClickArea",
					"properties": {
						"initially-visible": true,
						"initial-animation": "Animation 1",
						"initial-frame": 0,
						"enable-collisions": true,
						"live-preview": false
					},
					"uid": 25,
					"sid": 677781232871319,
					"tags": "",
					"instanceVariables": {},
					"behaviors": {
						"DragDrop": {
							"properties": {
								"axes": "both",
								"enabled": true
							}
						}
					},
					"effects": {
						"Pulse": {
							"isEnabled": true,
							"parameters": {
								"intensity": 1,
								"lighting": 0.5,
								"speed": 10,
								"frequency": 30,
								"center-x": 0.5,
								"center-y": 0.5
							}
						},
						"Noise": {
							"isEnabled": true,
							"parameters": {
								"intensity": 0.4,
								"color": 1
							}
						}
					},
					"sceneGraphData": {
						"parent-uid": null,
						"uid": 25,
						"flags": {
							"x": true,
							"y": true,
							"z": true,
							"w": true,
							"h": true,
							"a": true,
							"o": false,
							"v": false,
							"d": true,
							"sm": "normal"
						},
						"preview": {
							"transformX": 0,
							"transformY": 0,
							"transformZElevation": 0,
							"transformW": 0,
							"transformH": 0,
							"transformA": 0,
							"transformSX": 0,
							"transformSY": 0,
							"transformO": 0,
							"previewSceneGraph": false
						}
					},
					"instanceFolderItem": {
						"sid": 677781232871319,
						"expanded": true
					},
					"showing": true,
					"locked": false,
					"world": {
						"x": 134,
						"y": 521,
						"width": 178,
						"height": 185,
						"originX": 0.5,
						"originY": 0.5,
						"color": [
							1,
							1,
							1,
							1
						],
						"angle": 0,
						"zElevation": 0
					}
				},
				{
					"type": "PackagingGameIconImage",
					"properties": {
						"svg-file": 936749831006809,
						"initially-visible": true,
						"origin": "center"
					},
					"uid": 27,
					"sid": 975128138458395,
					"tags": "",
					"instanceVariables": {},
					"behaviors": {
						"Fade": {
							"properties": {
								"fade-in-time": 0,
								"wait-time": 0.2,
								"fade-out-time": 0.5,
								"destroy": true,
								"enabled": false,
								"live-preview": false
							}
						}
					},
					"sceneGraphData": {
						"parent-uid": null,
						"uid": 27,
						"flags": {
							"x": true,
							"y": true,
							"z": true,
							"w": true,
							"h": true,
							"a": true,
							"o": false,
							"v": false,
							"d": true,
							"sm": "normal"
						},
						"preview": {
							"transformX": 0,
							"transformY": 0,
							"transformZElevation": 0,
							"transformW": 0,
							"transformH": 0,
							"transformA": 0,
							"transformSX": 0,
							"transformSY": 0,
							"transformO": 0,
							"previewSceneGraph": false
						}
					},
					"instanceFolderItem": {
						"sid": 975128138458395,
						"expanded": true
					},
					"showing": true,
					"locked": false,
					"world": {
						"x": 101,
						"y": 484,
						"width": 100,
						"height": 100,
						"originX": 0.5,
						"originY": 0.5,
						"color": [
							1,
							1,
							1,
							1
						],
						"angle": 0,
						"zElevation": 0
					}
				},
				{
					"type": "PackagingGameIconText",
					"properties": {
						"text": "Wrap Pop",
						"enable-bbcode": true,
						"font": "UbuntuSansMono-VariableFont_wght",
						"size": 14,
						"line-height": 0,
						"bold": true,
						"italic": false,
						"color": [
							0,
							0,
							0,
							1
						],
						"horizontal-alignment": "center",
						"vertical-alignment": "top",
						"wrapping": "word",
						"text-direction": "ltr",
						"icon-set": -1,
						"initially-visible": true,
						"origin": "top-left",
						"read-aloud": false
					},
					"uid": 28,
					"sid": 749063782224309,
					"tags": "",
					"instanceVariables": {},
					"behaviors": {},
					"sceneGraphData": {
						"parent-uid": null,
						"uid": 28,
						"flags": {
							"x": true,
							"y": true,
							"z": true,
							"w": true,
							"h": true,
							"a": true,
							"o": false,
							"v": false,
							"d": true,
							"sm": "normal"
						},
						"preview": {
							"transformX": 0,
							"transformY": 0,
							"transformZElevation": 0,
							"transformW": 0,
							"transformH": 0,
							"transformA": 0,
							"transformSX": 0,
							"transformSY": 0,
							"transformO": 0,
							"previewSceneGraph": false
						}
					},
					"instanceFolderItem": {
						"sid": 749063782224309,
						"expanded": true
					},
					"showing": true,
					"locked": false,
					"world": {
						"x": 18,
						"y": 555,
						"width": 160,
						"height": 44,
						"originX": 0,
						"originY": 0,
						"color": [
							1,
							1,
							1,
							1
						],
						"angle": 0,
						"zElevation": 0
					}
				},
				{
					"type": "PackingGameClickArea2",
					"properties": {
						"initially-visible": true,
						"initial-animation": "Animation 1",
						"initial-frame": 0,
						"enable-collisions": true,
						"live-preview": false
					},
					"uid": 30,
					"sid": 699065396746965,
					"tags": "",
					"instanceVariables": {},
					"behaviors": {
						"DragDrop": {
							"properties": {
								"axes": "both",
								"enabled": true
							}
						}
					},
					"effects": {
						"Pulse": {
							"isEnabled": true,
							"parameters": {
								"intensity": 1,
								"lighting": 0.5,
								"speed": 10,
								"frequency": 30,
								"center-x": 0.5,
								"center-y": 0.5
							}
						},
						"Noise": {
							"isEnabled": true,
							"parameters": {
								"intensity": 0.4,
								"color": 1
							}
						}
					},
					"sceneGraphData": {
						"parent-uid": null,
						"uid": 30,
						"flags": {
							"x": true,
							"y": true,
							"z": true,
							"w": true,
							"h": true,
							"a": true,
							"o": false,
							"v": false,
							"d": true,
							"sm": "normal"
						},
						"preview": {
							"transformX": 0,
							"transformY": 0,
							"transformZElevation": 0,
							"transformW": 0,
							"transformH": 0,
							"transformA": 0,
							"transformSX": 0,
							"transformSY": 0,
							"transformO": 0,
							"previewSceneGraph": false
						}
					},
					"instanceFolderItem": {
						"sid": 699065396746965,
						"expanded": true
					},
					"showing": true,
					"locked": false,
					"world": {
						"x": 48,
						"y": 686,
						"width": 178,
						"height": 185,
						"originX": 0.5,
						"originY": 0.5,
						"color": [
							1,
							1,
							1,
							1
						],
						"angle": 0,
						"zElevation": 0
					}
				},
				{
					"type": "BubbleGuyClickArea",
					"properties": {
						"initially-visible": true,
						"initial-animation": "Animation 1",
						"initial-frame": 0,
						"enable-collisions": true,
						"live-preview": false
					},
					"uid": 31,
					"sid": 568336653422020,
					"tags": "",
					"instanceVariables": {},
					"behaviors": {
						"DragDrop": {
							"properties": {
								"axes": "both",
								"enabled": true
							}
						}
					},
					"effects": {
						"Pulse": {
							"isEnabled": true,
							"parameters": {
								"intensity": 1,
								"lighting": 0.5,
								"speed": 10,
								"frequency": 30,
								"center-x": 0.5,
								"center-y": 0.5
							}
						},
						"Noise": {
							"isEnabled": true,
							"parameters": {
								"intensity": 0.4,
								"color": 1
							}
						}
					},
					"sceneGraphData": {
						"parent-uid": null,
						"uid": 31,
						"flags": {
							"x": true,
							"y": true,
							"z": true,
							"w": true,
							"h": true,
							"a": true,
							"o": false,
							"v": false,
							"d": true,
							"sm": "normal"
						},
						"preview": {
							"transformX": 0,
							"transformY": 0,
							"transformZElevation": 0,
							"transformW": 0,
							"transformH": 0,
							"transformA": 0,
							"transformSX": 0,
							"transformSY": 0,
							"transformO": 0,
							"previewSceneGraph": false
						}
					},
					"instanceFolderItem": {
						"sid": 568336653422020,
						"expanded": true
					},
					"showing": true,
					"locked": false,
					"world": {
						"x": 61,
						"y": 682,
						"width": 178,
						"height": 185,
						"originX": 0.5,
						"originY": 0.5,
						"color": [
							1,
							1,
							1,
							1
						],
						"angle": 0,
						"zElevation": 0
					}
				},
				{
					"type": "BubbleGuyGameIconText",
					"properties": {
						"text": "Super Bubble Cat",
						"enable-bbcode": true,
						"font": "UbuntuSansMono-VariableFont_wght",
						"size": 14,
						"line-height": 0,
						"bold": true,
						"italic": false,
						"color": [
							0,
							0,
							0,
							1
						],
						"horizontal-alignment": "center",
						"vertical-alignment": "top",
						"wrapping": "word",
						"text-direction": "ltr",
						"icon-set": -1,
						"initially-visible": true,
						"origin": "top-left",
						"read-aloud": false
					},
					"uid": 33,
					"sid": 417766630101433,
					"tags": "",
					"instanceVariables": {},
					"behaviors": {},
					"sceneGraphData": {
						"parent-uid": null,
						"uid": 33,
						"flags": {
							"x": true,
							"y": true,
							"z": true,
							"w": true,
							"h": true,
							"a": true,
							"o": false,
							"v": false,
							"d": true,
							"sm": "normal"
						},
						"preview": {
							"transformX": 0,
							"transformY": 0,
							"transformZElevation": 0,
							"transformW": 0,
							"transformH": 0,
							"transformA": 0,
							"transformSX": 0,
							"transformSY": 0,
							"transformO": 0,
							"previewSceneGraph": false
						}
					},
					"instanceFolderItem": {
						"sid": 417766630101433,
						"expanded": true
					},
					"showing": true,
					"locked": false,
					"world": {
						"x": 18,
						"y": 729,
						"width": 160,
						"height": 58,
						"originX": 0,
						"originY": 0,
						"color": [
							1,
							1,
							1,
							1
						],
						"angle": 0,
						"zElevation": 0
					}
				},
				{
					"type": "BubbleGuyGameIconImage",
					"properties": {
						"svg-file": 435051321048199,
						"initially-visible": true,
						"origin": "center"
					},
					"uid": 34,
					"sid": 560085933537016,
					"tags": "",
					"instanceVariables": {},
					"behaviors": {
						"Fade": {
							"properties": {
								"fade-in-time": 0,
								"wait-time": 0.2,
								"fade-out-time": 0.5,
								"destroy": true,
								"enabled": false,
								"live-preview": false
							}
						}
					},
					"sceneGraphData": {
						"parent-uid": null,
						"uid": 34,
						"flags": {
							"x": true,
							"y": true,
							"z": true,
							"w": true,
							"h": true,
							"a": true,
							"o": false,
							"v": false,
							"d": true,
							"sm": "normal"
						},
						"preview": {
							"transformX": 0,
							"transformY": 0,
							"transformZElevation": 0,
							"transformW": 0,
							"transformH": 0,
							"transformA": 0,
							"transformSX": 0,
							"transformSY": 0,
							"transformO": 0,
							"previewSceneGraph": false
						}
					},
					"instanceFolderItem": {
						"sid": 560085933537016,
						"expanded": true
					},
					"showing": true,
					"locked": false,
					"world": {
						"x": 99,
						"y": 663,
						"width": 100,
						"height": 100,
						"originX": 0.5,
						"originY": 0.5,
						"color": [
							1,
							1,
							1,
							1
						],
						"angle": 0,
						"zElevation": 0
					}
				},
				{
					"type": "SnakeIconText",
					"properties": {
						"text": "Duck",
						"enable-bbcode": true,
						"font": "UbuntuSansMono-VariableFont_wght",
						"size": 14,
						"line-height": 0,
						"bold": true,
						"italic": false,
						"color": [
							0,
							0,
							0,
							1
						],
						"horizontal-alignment": "center",
						"vertical-alignment": "top",
						"wrapping": "word",
						"text-direction": "ltr",
						"icon-set": -1,
						"initially-visible": true,
						"origin": "top-left",
						"read-aloud": false
					},
					"uid": 46,
					"sid": 378522655224336,
					"tags": "",
					"instanceVariables": {},
					"behaviors": {},
					"sceneGraphData": {
						"parent-uid": null,
						"uid": 46,
						"flags": {
							"x": true,
							"y": true,
							"z": true,
							"w": true,
							"h": true,
							"a": true,
							"o": false,
							"v": false,
							"d": true,
							"sm": "normal"
						},
						"preview": {
							"transformX": 0,
							"transformY": 0,
							"transformZElevation": 0,
							"transformW": 0,
							"transformH": 0,
							"transformA": 0,
							"transformSX": 0,
							"transformSY": 0,
							"transformO": 0,
							"previewSceneGraph": false
						}
					},
					"instanceFolderItem": {
						"sid": 378522655224336,
						"expanded": true
					},
					"showing": true,
					"locked": false,
					"world": {
						"x": 14,
						"y": 899,
						"width": 160,
						"height": 44,
						"originX": 0,
						"originY": 0,
						"color": [
							1,
							1,
							1,
							1
						],
						"angle": 0,
						"zElevation": 0
					}
				},
				{
					"type": "SnakeIconImage",
					"properties": {
						"svg-file": 688640520907701,
						"initially-visible": true,
						"origin": "center"
					},
					"uid": 47,
					"sid": 742538187801380,
					"tags": "",
					"instanceVariables": {},
					"behaviors": {
						"Fade": {
							"properties": {
								"fade-in-time": 0,
								"wait-time": 0.2,
								"fade-out-time": 0.5,
								"destroy": true,
								"enabled": false,
								"live-preview": false
							}
						}
					},
					"sceneGraphData": {
						"parent-uid": null,
						"uid": 47,
						"flags": {
							"x": true,
							"y": true,
							"z": true,
							"w": true,
							"h": true,
							"a": true,
							"o": false,
							"v": false,
							"d": true,
							"sm": "normal"
						},
						"preview": {
							"transformX": 0,
							"transformY": 0,
							"transformZElevation": 0,
							"transformW": 0,
							"transformH": 0,
							"transformA": 0,
							"transformSX": 0,
							"transformSY": 0,
							"transformO": 0,
							"previewSceneGraph": false
						}
					},
					"instanceFolderItem": {
						"sid": 742538187801380,
						"expanded": true
					},
					"showing": true,
					"locked": false,
					"world": {
						"x": 87,
						"y": 837,
						"width": 100,
						"height": 100,
						"originX": 0.5,
						"originY": 0.5,
						"color": [
							1,
							1,
							1,
							1
						],
						"angle": 0,
						"zElevation": 0
					}
				},
				{
					"type": "BubbleCollectMeter",
					"properties": {
						"svg-file": 738084344553151,
						"initially-visible": true,
						"origin": "top-left"
					},
					"uid": 71,
					"sid": 223100040275249,
					"tags": "",
					"instanceVariables": {},
					"behaviors": {},
					"instanceFolderItem": {
						"sid": 223100040275249,
						"expanded": true
					},
					"showing": true,
					"locked": false,
					"world": {
						"x": 1758,
						"y": 282,
						"width": 141,
						"height": 437,
						"originX": 0,
						"originY": 0,
						"color": [
							1,
							1,
							1,
							1
						],
						"angle": 0,
						"zElevation": 0
					}
				},
				{
					"type": "BubbleMeterCollected1",
					"properties": {
						"svg-file": 912859896365432,
						"initially-visible": false,
						"origin": "top-left"
					},
					"uid": 72,
					"sid": 949965161578692,
					"tags": "",
					"instanceVariables": {},
					"behaviors": {},
					"instanceFolderItem": {
						"sid": 949965161578692,
						"expanded": true
					},
					"showing": true,
					"locked": false,
					"world": {
						"x": 1790.4696024308787,
						"y": 619.0607413915884,
						"width": 75,
						"height": 74,
						"originX": 0,
						"originY": 0,
						"color": [
							1,
							1,
							1,
							1
						],
						"angle": 0,
						"zElevation": 0
					}
				},
				{
					"type": "BubbleMeterCollected2",
					"properties": {
						"svg-file": 912859896365432,
						"initially-visible": false,
						"origin": "top-left"
					},
					"uid": 73,
					"sid": 763792968494728,
					"tags": "",
					"instanceVariables": {},
					"behaviors": {},
					"instanceFolderItem": {
						"sid": 763792968494728,
						"expanded": true
					},
					"showing": true,
					"locked": false,
					"world": {
						"x": 1789.8061091945428,
						"y": 535.3865779504632,
						"width": 75,
						"height": 74,
						"originX": 0,
						"originY": 0,
						"color": [
							1,
							1,
							1,
							1
						],
						"angle": 0,
						"zElevation": 0
					}
				},
				{
					"type": "BubbleMeterCollected3",
					"properties": {
						"svg-file": 912859896365432,
						"initially-visible": false,
						"origin": "top-left"
					},
					"uid": 74,
					"sid": 727558073916425,
					"tags": "",
					"instanceVariables": {},
					"behaviors": {},
					"instanceFolderItem": {
						"sid": 727558073916425,
						"expanded": true
					},
					"showing": true,
					"locked": false,
					"world": {
						"x": 1790.7453894071602,
						"y": 452.2593965686831,
						"width": 75,
						"height": 74,
						"originX": 0,
						"originY": 0,
						"color": [
							1,
							1,
							1,
							1
						],
						"angle": 0,
						"zElevation": 0
					}
				}
			],
			"sid": 595750231175063,
			"effectTypes": [],
			"isInitiallyVisible": false,
			"isInitiallyInteractive": false,
			"isHTMLElementsLayer": false,
			"color": [
				1,
				1,
				1,
				1
			],
			"backgroundColor": [
				1,
				1,
				1,
				1
			],
			"isTransparent": true,
			"parallaxX": 1,
			"parallaxY": 1,
			"scaleRate": 1,
			"forceOwnTexture": false,
			"renderingMode": "3d",
			"drawOrder": "z-order",
			"useRenderCells": false,
			"blendMode": "normal",
			"zElevation": 0,
			"global": false
		},
		{
			"name": "GameCompleteLayer",
			"overriden": 0,
			"subLayers": [],
			"instances": [
				{
					"type": "WindowDocUnlocked",
					"properties": {
						"svg-file": 222140336377406,
						"initially-visible": true,
						"origin": "top-left"
					},
					"uid": 39,
					"sid": 859002308101505,
					"tags": "",
					"instanceVariables": {},
					"behaviors": {},
					"effects": {
						"Glitch": {
							"isEnabled": true,
							"parameters": {
								"glitchStrength": 0.2,
								"random1": 1,
								"random2": 1,
								"random3": 1,
								"random4": 1
							}
						}
					},
					"instanceFolderItem": {
						"sid": 859002308101505,
						"expanded": true
					},
					"showing": true,
					"locked": false,
					"world": {
						"x": 458,
						"y": 61,
						"width": 1043,
						"height": 834,
						"originX": 0,
						"originY": 0,
						"color": [
							1,
							1,
							1,
							1
						],
						"angle": 0,
						"zElevation": 0
					}
				}
			],
			"sid": 993806159253630,
			"effectTypes": [],
			"isInitiallyVisible": false,
			"isInitiallyInteractive": false,
			"isHTMLElementsLayer": false,
			"color": [
				1,
				1,
				1,
				1
			],
			"backgroundColor": [
				1,
				1,
				1,
				1
			],
			"isTransparent": true,
			"parallaxX": 1,
			"parallaxY": 1,
			"scaleRate": 1,
			"forceOwnTexture": false,
			"renderingMode": "3d",
			"drawOrder": "z-order",
			"useRenderCells": false,
			"blendMode": "normal",
			"zElevation": 0,
			"global": false
		}
	],
	"scene-graphs-folder-root": {
		"items": [
			{
				"sid": 515816181310533,
				"expanded": true
			},
			{
				"sid": 278623165090405,
				"expanded": true
			},
			{
				"sid": 629999832178318,
				"expanded": true
			},
			{
				"sid": 986464872803689,
				"expanded": true
			},
			{
				"sid": 749799139121358,
				"expanded": true
			},
			{
				"sid": 861996856131825,
				"expanded": true
			},
			{
				"sid": 661169690769736,
				"expanded": true
			},
			{
				"sid": 207693634960939,
				"expanded": true
			},
			{
				"sid": 302537221188373,
				"expanded": true
			},
			{
				"sid": 957121073151944,
				"expanded": true
			},
			{
				"sid": 311597657658780,
				"expanded": true
			},
			{
				"sid": 682836241448069,
				"expanded": true
			},
			{
				"sid": 646323016019421,
				"expanded": true
			},
			{
				"sid": 705610037030840,
				"expanded": true
			},
			{
				"sid": 346363193517649,
				"expanded": true
			},
			{
				"sid": 931926200633726,
				"expanded": true
			},
			{
				"sid": 378371233805410,
				"expanded": true
			},
			{
				"sid": 914881312306152,
				"expanded": true
			},
			{
				"sid": 697700295300401,
				"expanded": true
			},
			{
				"sid": 294857237094009,
				"expanded": true
			},
			{
				"sid": 884415587513726,
				"expanded": true
			},
			{
				"sid": 203977574497095,
				"expanded": true
			},
			{
				"sid": 212230158137646,
				"expanded": true
			},
			{
				"sid": 958499680313472,
				"expanded": true
			},
			{
				"sid": 819474848746584,
				"expanded": true
			},
			{
				"sid": 404456869671166,
				"expanded": true
			},
			{
				"sid": 233815620332558,
				"expanded": true
			},
			{
				"sid": 297689674633698,
				"expanded": true
			},
			{
				"sid": 701195044154897,
				"expanded": true
			},
			{
				"sid": 998519075890846,
				"expanded": true
			},
			{
				"sid": 811577610237043,
				"expanded": true
			},
			{
				"sid": 886148906601396,
				"expanded": true
			},
			{
				"sid": 529558518241779,
				"expanded": true
			},
			{
				"sid": 294695512399517,
				"expanded": true
			},
			{
				"sid": 128581443924038,
				"expanded": true
			},
			{
				"sid": 266851883863828,
				"expanded": true
			},
			{
				"sid": 112867269671461,
				"expanded": true
			},
			{
				"sid": 528193043689633,
				"expanded": true
			},
			{
				"sid": 631701455917377,
				"expanded": true
			},
			{
				"sid": 905124757160879,
				"expanded": true
			},
			{
				"sid": 131362121694831,
				"expanded": true
			},
			{
				"sid": 704261742420380,
				"expanded": true
			},
			{
				"sid": 677781232871319,
				"expanded": true
			},
			{
				"sid": 975128138458395,
				"expanded": true
			},
			{
				"sid": 749063782224309,
				"expanded": true
			},
			{
				"sid": 699065396746965,
				"expanded": true
			},
			{
				"sid": 568336653422020,
				"expanded": true
			},
			{
				"sid": 417766630101433,
				"expanded": true
			},
			{
				"sid": 560085933537016,
				"expanded": true
			},
			{
				"sid": 378522655224336,
				"expanded": true
			},
			{
				"sid": 742538187801380,
				"expanded": true
			},
			{
				"sid": 223100040275249,
				"expanded": true
			},
			{
				"sid": 949965161578692,
				"expanded": true
			},
			{
				"sid": 763792968494728,
				"expanded": true
			},
			{
				"sid": 727558073916425,
				"expanded": true
			},
			{
				"sid": 859002308101505,
				"expanded": true
			}
		],
		"subfolders": []
	},
	"sid": 255150839636551,
	"nonworld-instances": [],
	"effectTypes": [],
	"width": 1920,
	"height": 1080,
	"unboundedScrolling": false,
	"vpX": 0.5,
	"vpY": 0.5,
	"projection": "perspective",
	"eventSheet": "Event sheet 1"
}